Metadata-Version: 1.1
Name: autogradeCS
Version: 0.0.1
Summary: A grading system on collab
Home-page: UNKNOWN
Author: Dung Nguyne
Author-email: shayneng592@gmail.com
License: MIT
Keywords: calculator
Platform: UNKNOWN
Classifier: Development Status :: 5 - Production/Stable
Classifier: Intended Audience :: Education
Classifier: Operating System :: Microsoft :: Windows :: Windows 10
Classifier: License :: OSI Approved :: MIT License
Classifier: Programming Language :: Python :: 3
